{"_type":"export","__export_format":4,"__export_date":"2023-01-11T18:32:10.003Z","__export_source":"insomnia.desktop.app:v2022.7.1","resources":[{"_id":"req_ba3e905e55964191838e47e3d396e8a4","parentId":"wrk_870e63ae1a714f13ace74902be177056","modified":1673461851863,"created":1672266454792,"url":"{{ _.url }}tokens","name":"LOGIN","description":"","method":"POST","body":{"mimeType":"application/json","text":"{\n\t\"username\": \"teste\",\n\t\"password\": \"123456789*Wes\"\n}"},"parameters":[],"headers":[{"name":"Content-Type","value":"application/json","id":"pair_f974b5dec84643b9a755d24e26e94d0c"}],"authentication":{},"metaSortKey":-1672266454792,"isPrivate":false,"settingStoreCookies":true,"settingSendCookies":true,"settingDisableRenderRequestBody":false,"settingEncodeUrl":true,"settingRebuildPath":true,"settingFollowRedirects":"global","_type":"request"},{"_id":"wrk_870e63ae1a714f13ace74902be177056","parentId":null,"modified":1672266435682,"created":1672266435682,"name":"microservice-authentication","description":"","scope":"collection","_type":"workspace"},{"_id":"req_b32d026f0ba5484ea4f61d55f305f7f9","parentId":"wrk_870e63ae1a714f13ace74902be177056","modified":1673143712273,"created":1672706989252,"url":"{{ _.url }}tokens/refresh","name":"REFRESH LOGIN","description":"","method":"POST","body":{},"parameters":[],"headers":[{"id":"pair_91720323cf5544f9b30a6a486b7b9131","name":"refresh_token","value":"{% response 'body', 'req_ba3e905e55964191838e47e3d396e8a4', 'b64::JC50eXBl::46b', 'never', 60 %}{% response 'body', 'req_ba3e905e55964191838e47e3d396e8a4', 'b64::JC5yZWZyZXNoX3Rva2Vu::46b', 'never', 60 %}","description":""}],"authentication":{},"metaSortKey":-1672266451238.5,"isPrivate":false,"settingStoreCookies":true,"settingSendCookies":true,"settingDisableRenderRequestBody":false,"settingEncodeUrl":true,"settingRebuildPath":true,"settingFollowRedirects":"global","_type":"request"},{"_id":"req_c3174ef229524c11addb1510490c382c","parentId":"wrk_870e63ae1a714f13ace74902be177056","modified":1673451385870,"created":1673451280705,"url":"{{ _.url }}tokens/changePass/teste","name":"RESET PASSWORD TOKEN","description":"","method":"POST","body":{},"parameters":[],"headers":[],"authentication":{},"metaSortKey":-1672266449461.75,"isPrivate":false,"settingStoreCookies":true,"settingSendCookies":true,"settingDisableRenderRequestBody":false,"settingEncodeUrl":true,"settingRebuildPath":true,"settingFollowRedirects":"global","_type":"request"},{"_id":"req_1e8a34dec62e4217be162a0bb7ea7cdd","parentId":"fld_fcd7cf0101ab411f9fdec6dffc04021b","modified":1673252367881,"created":1672266450024,"url":"{{ _.url }}users","name":"CREATE","description":"","method":"POST","body":{"mimeType":"application/json","text":"{\n\t\"username\": \"weslley08baa\",\n\t\"password\": \"12560Wes*\"\n}"},"parameters":[],"headers":[{"name":"Content-Type","value":"application/json"}],"authentication":{},"metaSortKey":-1672266447685,"isPrivate":false,"settingStoreCookies":true,"settingSendCookies":true,"settingDisableRenderRequestBody":false,"settingEncodeUrl":true,"settingRebuildPath":true,"settingFollowRedirects":"global","_type":"request"},{"_id":"fld_fcd7cf0101ab411f9fdec6dffc04021b","parentId":"wrk_870e63ae1a714f13ace74902be177056","modified":1672266444991,"created":1672266444991,"name":"User","description":"","environment":{},"environmentPropertyOrder":null,"metaSortKey":-1672266444991,"_type":"request_group"},{"_id":"req_137934c9fdf941b683addb3bd5cd1512","parentId":"fld_fcd7cf0101ab411f9fdec6dffc04021b","modified":1673450021473,"created":1672266448904,"url":"{{ _.url }}users/update","name":"UPDATE USERNAME","description":"","method":"PATCH","body":{"mimeType":"application/json","text":"{\n\t\"new_username\": \"teste\"\n}"},"parameters":[{"id":"pair_2ad3609bdbb7455d93b1ad7e36b9098b","name":"type_update","value":"CHANGE_USER","description":""}],"headers":[{"name":"Content-Type","value":"application/json","id":"pair_abb6fc7396fa49df8a296a34bb20755b"},{"id":"pair_07c44caef3b44556a309f16dc1c485a6","name":"Authorization","value":"{% response 'body', 'req_ba3e905e55964191838e47e3d396e8a4', 'b64::JC50eXBl::46b', 'never', 60 %}{% response 'body', 'req_ba3e905e55964191838e47e3d396e8a4', 'b64::JC5hY2Nlc3NfdG9rZW4=::46b', 'never', 60 %}","description":""}],"authentication":{},"metaSortKey":-1672266447635,"isPrivate":false,"settingStoreCookies":true,"settingSendCookies":true,"settingDisableRenderRequestBody":false,"settingEncodeUrl":true,"settingRebuildPath":true,"settingFollowRedirects":"global","_type":"request"},{"_id":"req_01975773e2cb41608b27494f30b8b5eb","parentId":"fld_fcd7cf0101ab411f9fdec6dffc04021b","modified":1673461749357,"created":1672363608417,"url":"{{ _.url }}users/update","name":"UPDATE PASSWORD","description":"","method":"PATCH","body":{"mimeType":"application/json","text":"{\n\t\"new_pass\": \"123456789*Wes\"\n}"},"parameters":[{"id":"pair_2ad3609bdbb7455d93b1ad7e36b9098b","name":"type_update","value":"CHANGE_PASSWORD","description":""}],"headers":[{"name":"Content-Type","value":"application/json","id":"pair_ddf17c69b24d4d3b8b09b3fde74118ff"},{"id":"pair_c15e4feb4f9e4481ab2be27bf06d9a00","name":"reset_password_token","value":"{% response 'body', 'req_c3174ef229524c11addb1510490c382c', 'b64::JC50eXBl::46b', 'never', 60 %}{% response 'body', 'req_c3174ef229524c11addb1510490c382c', 'b64::JC5yZXNldF9wYXNzX3Rva2Vu::46b', 'never', 60 %}","description":""}],"authentication":{},"metaSortKey":-1672266447610,"isPrivate":false,"settingStoreCookies":true,"settingSendCookies":true,"settingDisableRenderRequestBody":false,"settingEncodeUrl":true,"settingRebuildPath":true,"settingFollowRedirects":"global","_type":"request"},{"_id":"req_3a205cde21db4353b533766c384f2aa2","parentId":"fld_fcd7cf0101ab411f9fdec6dffc04021b","modified":1673450786672,"created":1672363611157,"url":"{{ _.url }}users/update","name":"UPDATE ROLE","description":"","method":"PATCH","body":{"mimeType":"application/json","text":"{\n\t\"new_role\": \"teste\",\n\t\"id_operador\": \"\"\n}"},"parameters":[{"id":"pair_2ad3609bdbb7455d93b1ad7e36b9098b","name":"type_update","value":"CHANGE_ROLE","description":""}],"headers":[{"id":"pair_1b0663a13bda4a25a05d0f346633a29c","name":"Authorization","value":"{% response 'body', 'req_ba3e905e55964191838e47e3d396e8a4', 'b64::JC50eXBl::46b', 'never', 60 %}{% response 'body', 'req_ba3e905e55964191838e47e3d396e8a4', 'b64::JC5hY2Nlc3NfdG9rZW4=::46b', 'never', 60 %}","description":""},{"name":"Content-Type","value":"application/json"}],"authentication":{},"metaSortKey":-1672266447597.5,"isPrivate":false,"settingStoreCookies":true,"settingSendCookies":true,"settingDisableRenderRequestBody":false,"settingEncodeUrl":true,"settingRebuildPath":true,"settingFollowRedirects":"global","_type":"request"},{"_id":"req_fefd570853994fb39bb563d1e2077357","parentId":"fld_fcd7cf0101ab411f9fdec6dffc04021b","modified":1673450799339,"created":1672368779057,"url":"{{ _.url }}users/update","name":"UPDATE DEACTIVATE OR ACTIVATE","description":"","method":"PATCH","body":{"mimeType":"application/json","text":"{}"},"parameters":[{"id":"pair_d587b25d8728442593118d70f2f3faff","name":"type_update","value":"DEACTIVATE_OR_ACTIVATE_USER","description":""}],"headers":[{"name":"Content-Type","value":"application/json"},{"name":"Authorization","value":"{% response 'body', 'req_ba3e905e55964191838e47e3d396e8a4', 'b64::JC50eXBl::46b', 'never', 60 %}{% response 'body', 'req_ba3e905e55964191838e47e3d396e8a4', 'b64::JC5hY2Nlc3NfdG9rZW4=::46b', 'never', 60 %}"}],"authentication":{},"metaSortKey":-1672266447588.125,"isPrivate":false,"settingStoreCookies":true,"settingSendCookies":true,"settingDisableRenderRequestBody":false,"settingEncodeUrl":true,"settingRebuildPath":true,"settingFollowRedirects":"global","_type":"request"},{"_id":"req_326aa4ab682e44919759cb4e0f918398","parentId":"fld_fcd7cf0101ab411f9fdec6dffc04021b","modified":1673461764372,"created":1672363644389,"url":"{{ _.url }}users/update","name":"UPDATE NOT RESET PASSWORD OR RESET PASSWORD","description":"","method":"PATCH","body":{"mimeType":"application/json","text":"{}"},"parameters":[{"id":"pair_2ad3609bdbb7455d93b1ad7e36b9098b","name":"type_update","value":"NOT_RESET_PASSWORD_OR_RESET_PASSWORD","description":""}],"headers":[{"id":"pair_9b8e2e4aed5149e1a8bbb6e4843e6c45","name":"Authorization","value":"{% response 'body', 'req_ba3e905e55964191838e47e3d396e8a4', 'b64::JC50eXBl::46b', 'never', 60 %}{% response 'body', 'req_ba3e905e55964191838e47e3d396e8a4', 'b64::JC5hY2Nlc3NfdG9rZW4=::46b', 'never', 60 %}","description":""},{"name":"Content-Type","value":"application/json","id":"pair_5bbb83db48ff4139a5cc7779cfdd3804"}],"authentication":{},"metaSortKey":-1672266447586.5625,"isPrivate":false,"settingStoreCookies":true,"settingSendCookies":true,"settingDisableRenderRequestBody":false,"settingEncodeUrl":true,"settingRebuildPath":true,"settingFollowRedirects":"global","_type":"request"},{"_id":"req_8088fd09d95e40d2abb772a4ee064b92","parentId":"fld_fcd7cf0101ab411f9fdec6dffc04021b","modified":1673461785348,"created":1672266447585,"url":"{{ _.url }}users/find","name":"FIND BY ID","description":"","method":"GET","body":{},"parameters":[{"id":"pair_99e310c1fde248f7a0f5a2ee28b99090","name":"find_type","value":"USER_ID","description":""}],"headers":[{"id":"pair_02a90fd8b11b4031a9374e8b32edefc7","name":"Authorization","value":"{% response 'body', 'req_ba3e905e55964191838e47e3d396e8a4', 'b64::JC50eXBl::46b', 'never', 60 %}{% response 'body', 'req_ba3e905e55964191838e47e3d396e8a4', 'b64::JC5hY2Nlc3NfdG9rZW4=::46b', 'never', 60 %}","description":""}],"authentication":{},"metaSortKey":-1672266447585,"isPrivate":false,"settingStoreCookies":true,"settingSendCookies":true,"settingDisableRenderRequestBody":false,"settingEncodeUrl":true,"settingRebuildPath":true,"settingFollowRedirects":"global","_type":"request"},{"_id":"req_e2904fb0630e47e19ddb4a4af1830446","parentId":"fld_fcd7cf0101ab411f9fdec6dffc04021b","modified":1673461794164,"created":1672681922017,"url":"{{ _.url }}users/find","name":"FIND BY USERNAME","description":"","method":"GET","body":{},"parameters":[{"id":"pair_9148c729ec564710bf86d7eff6a2005b","name":"find_type","value":"USERNAME","description":""}],"headers":[{"id":"pair_66feb9fb00ce4288a754b58992aba585","name":"Authorization","value":"{% response 'body', 'req_ba3e905e55964191838e47e3d396e8a4', 'b64::JC50eXBl::46b', 'never', 60 %}{% response 'body', 'req_ba3e905e55964191838e47e3d396e8a4', 'b64::JC5hY2Nlc3NfdG9rZW4=::46b', 'never', 60 %}","description":""}],"authentication":{},"metaSortKey":-1672041338931.5,"isPrivate":false,"settingStoreCookies":true,"settingSendCookies":true,"settingDisableRenderRequestBody":false,"settingEncodeUrl":true,"settingRebuildPath":true,"settingFollowRedirects":"global","_type":"request"},{"_id":"env_0eb130ee24d27f961bd9a6131b2598d1b58524ae","parentId":"wrk_870e63ae1a714f13ace74902be177056","modified":1672266435702,"created":1672266435702,"name":"Base Environment","data":{},"dataPropertyOrder":null,"color":null,"isPrivate":false,"metaSortKey":1672266435702,"_type":"environment"},{"_id":"jar_7816559a60937d2eec99f72f7861cde11d7db588","parentId":"wrk_870e63ae1a714f13ace74902be177056","modified":1672266435707,"created":1672266435707,"name":"Default Jar","cookies":[],"_type":"cookie_jar"},{"_id":"spc_7513efe27c364f7e9a3e461a481f9978","parentId":"wrk_870e63ae1a714f13ace74902be177056","modified":1672266435685,"created":1672266435685,"fileName":"microservice-authentication","contents":"","contentType":"yaml","_type":"api_spec"},{"_id":"env_e1507db41d4144e0946ca0263207ce13","parentId":"env_0eb130ee24d27f961bd9a6131b2598d1b58524ae","modified":1672362648001,"created":1672266556681,"name":"LOCAL","data":{"url":"http://localhost:8080/microservice-authentication/v1/"},"dataPropertyOrder":{"&":["url"]},"color":"#ff0000","isPrivate":false,"metaSortKey":1672266556681,"_type":"environment"}]}